CHANGES.txt
MANIFEST.in
README.txt
setup.py
src/cykooz/__init__.py
src/cykooz.sequence.egg-info/PKG-INFO
src/cykooz.sequence.egg-info/SOURCES.txt
src/cykooz.sequence.egg-info/dependency_links.txt
src/cykooz.sequence.egg-info/entry_points.txt
src/cykooz.sequence.egg-info/namespace_packages.txt
src/cykooz.sequence.egg-info/not-zip-safe
src/cykooz.sequence.egg-info/requires.txt
src/cykooz.sequence.egg-info/top_level.txt
src/cykooz/sequence/__init__.py
src/cykooz/sequence/configure.zcml
src/cykooz/sequence/ftesting.zcml
src/cykooz/sequence/interfaces.py
src/cykooz/sequence/sequence.py
src/cykooz/sequence/sequence.txt
src/cykooz/sequence/tests.py