Metadata-Version: 1.0
Name: cykooz.sequence
Version: 1.0.2
Summary: Generates a persistent sequence
Home-page: https://bitbucket.org/cykooz/cykooz.sequence
Author: Cykooz
Author-email: saikuz@mail.ru
License: ZPL
Platform: UNKNOWN
Classifier: Development Status :: 5 - Production/Stable
Classifier: Environment :: Web Environment
Classifier: Intended Audience :: Developers
Classifier: Framework :: Zope3
Classifier: License :: OSI Approved :: Zope Public License
Classifier: Programming Language :: Python
Classifier: Natural Language :: English
Classifier: Operating System :: OS Independent
Classifier: Topic :: Internet :: WWW/HTTP
